divar/__init__.py
divar/async_divar/__init__.py
divar/async_divar/client.py
divar/async_divar/errors.py
divar/async_divar/raw.py
divar/sync/__init__.py
divar/sync/client.py
divar/sync/errors.py
divar/sync/raw.py
divar-2.0.1.dist-info/METADATA
divar-2.0.1.dist-info/WHEEL
divar-2.0.1.dist-info/top_level.txt
divar-2.0.1.dist-info/RECORD
