Metadata-Version: 2.1
Name: divar
Version: 2.0.1
Summary: Unofficial api of Divar(Scrapping Divar)
Author: RealPalas
Author-email: palasongithub@gmail.com
Keywords: python,divar,api,iran,web scraping,bot,V1Z
Classifier: Development Status :: 5 - Production/Stable
Classifier: Intended Audience :: Developers
Classifier: Programming Language :: Python :: 3
Classifier: Operating System :: Unix
Classifier: Operating System :: MacOS :: MacOS X
Classifier: Operating System :: Microsoft :: Windows
Requires-Python: >=3.8
Requires-Dist: requests
Requires-Dist: aiohttp
